leelee/__init__.py
leelee/__version__.py
leelee/aa.py
leelee-0.1.5.dist-info/METADATA
leelee-0.1.5.dist-info/WHEEL
leelee-0.1.5.dist-info/top_level.txt
leelee-0.1.5.dist-info/RECORD
